msps/__main__.py
msps/cli.py
msps/config.py
msps/core.py
msps/maven.py
msps/model.py
msps/ui.py
tests/manual_test_ui.py
tests/test_maven.py
tests/test_ui.py
msps-1.0.3.dist-info/LICENSE
msps-1.0.3.dist-info/METADATA
msps-1.0.3.dist-info/WHEEL
msps-1.0.3.dist-info/entry_points.txt
msps-1.0.3.dist-info/RECORD
