Metadata-Version: 2.3
Name: msps
Version: 1.0.3
Summary: Maven Settings Profile Switcher
License: MIT
Author: István Földházi
Author-email: istvan.foldhazi@gmail.com
Requires-Python: >=3.10
Classifier: License :: OSI Approved :: MIT License
Classifier: Programming Language :: Python :: 3
Classifier: Programming Language :: Python :: 3.10
Classifier: Programming Language :: Python :: 3.11
Classifier: Programming Language :: Python :: 3.12
Classifier: Programming Language :: Python :: 3.13
Requires-Dist: rich (>=13.7.0,<14.0.0)
